env_check/__init__.py
env_check/apps.py
env_check/checks.py
django_env_checker-0.2.0.dist-info/METADATA
django_env_checker-0.2.0.dist-info/WHEEL
django_env_checker-0.2.0.dist-info/top_level.txt
django_env_checker-0.2.0.dist-info/RECORD
