Metadata-Version: 2.4
Name: django-env-checker
Version: 0.2.0
Summary: A simple Django env var checker
Home-page: https://github.com/RickVerbon/django-env-checker
Author: Rick Verbon
Author-email: rick89@gmail.com
Classifier: Programming Language :: Python :: 3
Classifier: Framework :: Django
Classifier: Operating System :: OS Independent
Requires-Python: >=3.9
Dynamic: author
Dynamic: author-email
Dynamic: classifier
Dynamic: description
Dynamic: description-content-type
Dynamic: home-page
Dynamic: requires-python
Dynamic: summary
